bigquery/BigQueryDBStream.py
bigquery/__init__.py
bigquery/core/Column.py
bigquery/core/Table.py
bigquery/core/__init__.py
bigquery/core/mapping_type.py
bigquery/core/tools/__init__.py
bigquery/core/tools/print_colors.py
bigquery-0.0.13.dist-info/LICENSE
bigquery-0.0.13.dist-info/METADATA
bigquery-0.0.13.dist-info/WHEEL
bigquery-0.0.13.dist-info/top_level.txt
bigquery-0.0.13.dist-info/RECORD
