Metadata-Version: 2.1
Name: bigquery
Version: 0.0.13
Summary: Easily send data to Big Query
Home-page: https://github.com/dacker-team/bigquery
Author: Dacker
Author-email: hello@dacker.co
License: UNKNOWN
Keywords: send data bigquery easy
Platform: UNKNOWN
Classifier: Programming Language :: Python :: 3
Classifier: License :: OSI Approved :: MIT License
Classifier: Operating System :: OS Independent
Requires-Python: >=3
Requires-Dist: dbstream (>=0.0.19)
Requires-Dist: google-cloud-bigquery (>=2.4.0)
Requires-Dist: googleauthentication (>=0.0.12)
Requires-Dist: google-cloud-bigquery-storage (>=2.1.0)
Requires-Dist: pandas (>=1.1.4)
Requires-Dist: pyarrow (>=2.0.0)
